phenobench/__init__.py
phenobench/phenobench_loader.py
phenobench/visualization.py
phenobench/evaluation/__init__.py
phenobench/evaluation/evaluate_leaf_bounding_boxes.py
phenobench/evaluation/evaluate_leaf_instance_masks_panoptic.py
phenobench/evaluation/evaluate_plant_bounding_boxes.py
phenobench/evaluation/evaluate_plant_instance_masks_panoptic.py
phenobench/evaluation/evaluate_semantics.py
phenobench/evaluation/phenobench_eval.py
phenobench/evaluation/auxiliary/__init__.py
phenobench/evaluation/auxiliary/common.py
phenobench/evaluation/auxiliary/convert.py
phenobench/evaluation/auxiliary/filter.py
phenobench/evaluation/auxiliary/panoptic_eval.py
phenobench/tools/validator.py
phenobench-0.1.0.dist-info/LICENSE
phenobench-0.1.0.dist-info/METADATA
phenobench-0.1.0.dist-info/WHEEL
phenobench-0.1.0.dist-info/entry_points.txt
phenobench-0.1.0.dist-info/top_level.txt
phenobench-0.1.0.dist-info/RECORD
