Metadata-Version: 2.1
Name: phenobench
Version: 0.1.0
Summary: The official development kit of the PhenoBench dataset (www.phenobench.org).
Author-email: Jens Behley <jens.behley@igg.uni-bonn.de>, Jan Weyler <jan.weyler@igg.uni-bonn.de>, Federico Magistri <federico.magistri@uni-bonn.de>, Matteo Sodano <matteo.sodano@igg.uni-bonn.de>, Gianmarco Roggiolani <groggiol@uni-bonn.de>, Elias Marks <elias.marks@uni-bonn.de>, "Yue (Linn) Chong" <ychong@uni-bonn.de>
Maintainer-email: Jens Behley <jens.behley@igg.uni-bonn.de>
License: MIT License
Project-URL: Homepage, https://www.phenobench.org
Project-URL: Bug Reports, https://github.com/PRBonn/phenobench/issues
Project-URL: Source, https://github.com/PRBonn/phenobench
Classifier: Development Status :: 4 - Beta
Classifier: Operating System :: OS Independent
Classifier: License :: OSI Approved :: MIT License
Classifier: Programming Language :: Python :: 3
Classifier: Programming Language :: Python :: 3.7
Classifier: Programming Language :: Python :: 3.8
Classifier: Programming Language :: Python :: 3.9
Classifier: Programming Language :: Python :: 3.10
Classifier: Programming Language :: Python :: 3.11
Classifier: Programming Language :: Python :: 3 :: Only
Requires-Python: >=3.7
License-File: LICENSE
Requires-Dist: numpy
Requires-Dist: matplotlib
Requires-Dist: Pillow (>6.2.1)
Provides-Extra: eval
Requires-Dist: torch ; extra == 'eval'
Requires-Dist: torchvision ; extra == 'eval'
Requires-Dist: torchmetrics (==0.10.3) ; extra == 'eval'
Requires-Dist: numpy ; extra == 'eval'
Requires-Dist: pyyaml ; extra == 'eval'
Requires-Dist: tqdm ; extra == 'eval'
